admin_reorder/__init__.py
admin_reorder/middleware.py
admin_reorder/models.py
admin_reorder/static/css/admin-reorder.css
admin_reorder/static/img/.gitignore
admin_reorder/static/js/admin-reorder.js
admin_reorder/templates/admin-reorder/base.html
django_admin_model_reorder-0.3.2.dist-info/LICENSE
django_admin_model_reorder-0.3.2.dist-info/WHEEL
django_admin_model_reorder-0.3.2.dist-info/METADATA
django_admin_model_reorder-0.3.2.dist-info/RECORD
